rela2x/__init__.py
rela2x/constants_and_variables.py
rela2x/nmr_isotopes.py
rela2x/rela2x.py
rela2x/settings.py
rela2x-0.0.1.dist-info/licenses/LICENSE
rela2x-0.0.1.dist-info/METADATA
rela2x-0.0.1.dist-info/WHEEL
rela2x-0.0.1.dist-info/top_level.txt
rela2x-0.0.1.dist-info/RECORD
