Metadata-Version: 2.4
Name: rela2x
Version: 0.0.1
Summary: Analytic and Automatic NMR relaxation theory.
Author-email: Perttu Hilla <perttu.hilla@oulu.fi>
License-Expression: MIT
Classifier: Programming Language :: Python :: 3
Classifier: Operating System :: OS Independent
Requires-Python: >=3.9
License-File: LICENSE
Requires-Dist: numpy
Requires-Dist: matplotlib
Requires-Dist: sympy
Dynamic: license-file
